shmarray/__init__.py
shmarray-0.0.3.dist-info/LICENSE
shmarray-0.0.3.dist-info/METADATA
shmarray-0.0.3.dist-info/WHEEL
shmarray-0.0.3.dist-info/top_level.txt
shmarray-0.0.3.dist-info/RECORD
