Metadata-Version: 2.1
Name: shmarray
Version: 0.0.3
Summary: A polished shmarray, originated by David Baddeley
Home-page: https://github.com/zxytim/shmarray
Author: Xinyu Zhou
Author-email: zxytim@gmail.com
License: UNKNOWN
Platform: UNKNOWN
Classifier: Programming Language :: Python :: 3
Classifier: License :: OSI Approved :: BSD License
Classifier: Intended Audience :: Developers
Classifier: Intended Audience :: Science/Research
Classifier: Topic :: Software Development :: Libraries :: Python Modules
Requires-Python: >=3.5
Requires-Dist: numpy
